causalbench/__init__.py
causalbench/commons/__init__.py
causalbench/commons/disk.py
causalbench/commons/executor.py
causalbench/commons/gpu.py
causalbench/commons/helpers.py
causalbench/commons/hwinfo.py
causalbench/commons/password.py
causalbench/commons/utils.py
causalbench/formats/__init__.py
causalbench/formats/spatiotemporaldata.py
causalbench/formats/spatiotemporalgraph.py
causalbench/modules/__init__.py
causalbench/modules/context.py
causalbench/modules/dataset.py
causalbench/modules/metric.py
causalbench/modules/model.py
causalbench/modules/module.py
causalbench/modules/run.py
causalbench/modules/scenario.py
causalbench/modules/task.py
causalbench/modules/schema/context.yaml
causalbench/modules/schema/dataset.yaml
causalbench/modules/schema/metric.yaml
causalbench/modules/schema/model.yaml
causalbench/modules/schema/run.yaml
causalbench/modules/schema/task.yaml
causalbench/services/__init__.py
causalbench/services/auth.py
causalbench/services/requests.py
causalbench_asu-0.2.0.dist-info/METADATA
causalbench_asu-0.2.0.dist-info/WHEEL
causalbench_asu-0.2.0.dist-info/licenses/LICENSE
causalbench_asu-0.2.0.dist-info/RECORD
