Metadata-Version: 2.4
Name: causalbench-asu
Version: 0.2.0
Summary: Spatio Temporal Causal Benchmarking Platform
Project-URL: Homepage, https://causalbench.org
Project-URL: Documentation, https://docs.causalbench.org
Project-URL: Repository, https://github.com/EmitLab/CausalBench
Project-URL: Issues, https://github.com/EmitLab/CausalBench/issues
Author-email: CausalBench Team <support@causalbench.org>
Maintainer-email: Ahmet Kapkiç <akapkic@asu.edu>, Pratanu Mandal <pmandal5@asu.edu>
License:                               CausalBench
License-File: LICENSE
Keywords: benchmark,causal,causalbench,causality,inference
Classifier: Development Status :: 4 - Beta
Classifier: License :: OSI Approved :: Apache Software License
Classifier: Operating System :: OS Independent
Classifier: Programming Language :: Python :: 3
Requires-Python: >=3.10
Requires-Dist: bunch-py3
Requires-Dist: certifi
Requires-Dist: jsonschema
Requires-Dist: nvidia-ml-py
Requires-Dist: pandas
Requires-Dist: pip-system-certs
Requires-Dist: pipreqs
Requires-Dist: psutil
Requires-Dist: py-cpuinfo
Requires-Dist: pyadl
Requires-Dist: pyjwt
Requires-Dist: pyopencl
Requires-Dist: pyyaml
Requires-Dist: requests
Requires-Dist: siphash24
Requires-Dist: wmi
